bulk_rename_uklewis124/__init__.py
bulk_rename_uklewis124/bulk_rename.py
bulk_rename_uklewis124/setup.py
bulk_rename_uklewis124-0.0.1.dist-info/LICENSE
bulk_rename_uklewis124-0.0.1.dist-info/METADATA
bulk_rename_uklewis124-0.0.1.dist-info/WHEEL
bulk_rename_uklewis124-0.0.1.dist-info/top_level.txt
bulk_rename_uklewis124-0.0.1.dist-info/RECORD
